{
  "additionalFiles": "",
  "builtInToolsFolders": "",
  "compiler.optimization_flags": "-Os",
  "customBuildProperties": "",
  "fqbn": "arduino:esp32:nano_nora:PartitionScheme=default,PinNumbers=default,USBMode=default",
  "hardwareFolders": "C:\\Users\\Worst\\AppData\\Local\\Arduino15\\packages",
  "otherLibrariesFolders": "C:\\Users\\Worst\\OneDrive\\Documents\\Arduino\\libraries",
  "runtime.ide.version": "10607",
  "sketchLocation": "C:\\Users\\Worst\\OneDrive\\Desktop\\RC-Rover-Project\\Arduino Tests\\RC_Control_Test1"
}